iapauth/__init__.py
iapauth/backends.py
iapauth/instrumentation.py
iapauth/middleware.py
django_iapauth-0.1.5.dist-info/METADATA
django_iapauth-0.1.5.dist-info/WHEEL
django_iapauth-0.1.5.dist-info/top_level.txt
django_iapauth-0.1.5.dist-info/RECORD
