Metadata-Version: 2.1
Name: django-iapauth
Version: 0.1.5
Summary: Authenticate with GCP IAP
Home-page: https://github.com/appsembler/django-iapauth
Author: Anders Pearson
Author-email: anders@appsembler.com
License: UNKNOWN
Platform: UNKNOWN
Classifier: Development Status :: 5 - Production/Stable
Classifier: Environment :: Web Environment
Classifier: Framework :: Django
Classifier: Framework :: Django :: 3.0
Classifier: Intended Audience :: Developers
Classifier: License :: OSI Approved :: BSD License
Classifier: Operating System :: OS Independent
Classifier: Programming Language :: Python
Classifier: Topic :: Software Development :: Libraries :: Python Modules
Classifier: Programming Language :: Python
Classifier: Programming Language :: Python :: 3
Classifier: Programming Language :: Python :: 3.5
Classifier: Programming Language :: Python :: 3.6
Classifier: Programming Language :: Python :: 3.7
Classifier: Programming Language :: Python :: 3.8
Classifier: Topic :: Utilities
Requires-Python: >=3.5
Requires-Dist: Django (>=3.0)
Requires-Dist: python-jose[cryptography]
Requires-Dist: requests
